pipeline_reader/__init__.py
pipeline_reader/objects.py
pipeline_reader/reader.py
pipeline_reader-0.0.5.dist-info/LICENSE
pipeline_reader-0.0.5.dist-info/METADATA
pipeline_reader-0.0.5.dist-info/WHEEL
pipeline_reader-0.0.5.dist-info/top_level.txt
pipeline_reader-0.0.5.dist-info/RECORD
