Metadata-Version: 2.1
Name: pipeline-reader
Version: 0.0.5
Summary: A package for reading Jenkinsfile-like pipeline files
Home-page: https://github.com/jfcarter2358/pipeline-reader
Author: John Carter
Author-email: jfcarter2358@gmail.com
License: UNKNOWN
Project-URL: Bug Tracker, https://github.com/jfcarter2358/pipeline-reader/issues
Platform: UNKNOWN
Classifier: Programming Language :: Python :: 3
Classifier: License :: OSI Approved :: MIT License
Classifier: Operating System :: OS Independent
Requires-Python: >=3.6
Requires-Dist: cartils (==0.1.2)
